Workbook

Sheet Ranking por valor de estoque
B1: Banner: Ranking de estoque por valor a custo (ajustado), com classificacao de giro por bucket de dias sem venda (aproximado por periodo fechado). Fonte: 4 periodos de Curva ABC (mai/2025 a jun/2026) + snapshot de estoque 03/08/2026. Outliers criticos (codigos 7153, 7874) excluidos. Gerado em 26/08/2026.
A2: Filtro | B2: codigo | C2: produto | D2: categoria | E2: fornecedor | F2: qtde | G2: custo_unit_usado | H2: valor_estoque_ajustado | I2: preco | J2: margem_cadastrada_pct | K2: bucket_giro | L2: dias_sem_venda_minimo | M2: ultimo_periodo_com_venda | N2: notas
A3: =_xlfn.XLOOKUP(C:C,'Resumo por bucket'!F:F,'Resumo por bucket'!I:I,"") -> 0 | B3: 1986 | C3: CUMEEIRA ZINCALUM 0.43 | D3: MATERIAL BASICO | F3: 2998 | G3: 26 | H3: 77948 | I3: 41 | J3: 57.69 | K3: Nunca vendeu (14 meses) | N3: Vendida por encomenda (confirmado Tony 26/08/2026). Giro zero e esperado, nao e estoque parado real.
A4: =_xlfn.XLOOKUP(C:C,'Resumo por bucket'!F:F,'Resumo por bucket'!I:I,"") | B4: 51 | C4: AREIA FINA | D4: MATERIAL BASICO | E4: CB MATERIAL DE CONSTRUCAO | F4: 1099.2681 | G4: 70.83 | H4: 77861.16 | I4: 130 | J4: 83.53 | K4: 31 a 60 dias | L4: 34 | M4: P4
A5: =_xlfn.XLOOKUP(C:C,'Resumo por bucket'!F:F,'Resumo por bucket'!I:I,"") -> 0 | B5: 3746 | C5: VARETA SOLDA OXI 1.59MM GERDAU | D5: MD-MD-MD-MD-MD- MD-MD-MD-MD-MD- | E5: COMERCIAL GERDAU | F5: 7329 | G5: 10.2 | H5: 74755.8 | I5: 25 | J5: 145.1 | K5: Nunca vendeu (14 meses) | N5: Slow-mover genuino (confirmado Tony 26/08/2026), nao erro de leitura.
A6: =_xlfn.XLOOKUP(C:C,'Resumo por bucket'!F:F,'Resumo por bucket'!I:I,"") | B6: 1322 | C6: AREIA MEDIA | D6: MATERIAL BASICO | E6: CB MATERIAL DE CONSTRUCAO | F6: 668.5256 | G6: 70.83 | H6: 47351.67 | I6: 130 | J6: 83.53 | K6: 31 a 60 dias | L6: 34 | M6: P4
A7: =_xlfn.XLOOKUP(C:C,'Resumo por bucket'!F:F,'Resumo por bucket'!I:I,"") | B7: 92 | C7: PEDRA BRITADA 1 (19) | D7: MATERIAL BASICO | E7: MILTON ALVES FERREIRA | F7: 190.9622 | G7: 100 | H7: 19096.22 | I7: 220 | J7: 120 | K7: 31 a 60 dias | L7: 34 | M7: P4
A8: =_xlfn.XLOOKUP(C:C,'Resumo por bucket'!F:F,'Resumo por bucket'!I:I,"") -> 0 | B8: 11024 | C8: SACOLA RECICLADAS VD 60X80 | D8: MATERIAL DE USO E CONSUMO | E8: VINICIUS DE SOUSA AMARO LTDA | F8: 1015 | G8: 11.5 | H8: 11672.5 | I8: 20 | J8: 73.91 | K8: Nunca vendeu (14 meses)
A9: =_xlfn.XLOOKUP(C:C,'Resumo por bucket'!F:F,'Resumo por bucket'!I:I,"") | B9: 98 | C9: PEDRA BRITADA 0 (CASCALHINHO) | D9: MATERIAL BASICO | E9: MILTON ALVES FERREIRA | F9: 105.1551 | G9: 106.67 | H9: 11216.89 | I9: 240 | J9: 125 | K9: 31 a 60 dias | L9: 34 | M9: P4
A10: =_xlfn.XLOOKUP(C:C,'Resumo por bucket'!F:F,'Resumo por bucket'!I:I,"") -> 0 | B10: 3214 | C10: TUBO PVC ROSCA 1 POL TIGRE | D10: MD-MD-MD-MD-MD- MD-MD-MD-MD-MD- | F10: 999.83 | G10: 8.06 | H10: 8058.63 | I10: 96 | J10: 1091.07 | K10: Nunca vendeu (14 meses) | N10: Produto de giro baixo confirmado (Tony 26/08/2026). Duvida de cadastro (custo/preco/qtde) segue em aberto, ver diagnostico giro-estoque anterior.
A11: =_xlfn.XLOOKUP(C:C,'Resumo por bucket'!F:F,'Resumo por bucket'!I:I,"") | B11: 7972 | C11: CIMENTO POTY CPII Z 32 TODAS AS OBRAS SC 50KG | D11: MATERIAL BASICO | E11: VCNE - FABRICA PAULISTA | F11: 174 | G11: 38.22 | H11: 6650.28 | I11: 51 | J11: 33.44 | K11: 31 a 60 dias | L11: 34 | M11: P4
A12: =_xlfn.XLOOKUP(C:C,'Resumo por bucket'!F:F,'Resumo por bucket'!I:I,"") | B12: 2791 | C12: TRELICA PREMOLDADA TG8 SL 6/3 X 4/4.2MM | D12: MATERIAL BASICO | E12: RJ FERRAGENS | F12: 595.3 | G12: 11 | H12: 6548.3 | I12: 22 | J12: 100 | K12: 31 a 60 dias | L12: 34 | M12: P4
A13: =_xlfn.XLOOKUP(C:C,'Resumo por bucket'!F:F,'Resumo por bucket'!I:I,"") | B13: 11225 | C13: SACO DE AREIA IMPRESSO 40x60 | D13: MATERIAL DE USO E CONSUMO | E13: I3S INDUSTRIA E COMERCIO DE MATERIAIS PLASTICOS E | F13: 8138 | G13: 0.68 | H13: 5533.84 | I13: 2 | J13: 196.3 | K13: 31 a 60 dias | L13: 34 | M13: P4
A14: =_xlfn.XLOOKUP(C:C,'Resumo por bucket'!F:F,'Resumo por bucket'!I:I,"") | B14: 1344 | C14: TELHA CANAL TIPO RUSSA 2a. | D14: COBERTURA | E14: CERAMICA CRISTO REY LTDA | F14: 5585.1 | G14: 0.93 | H14: 5194.14 | I14: 1.4 | J14: 50.54 | K14: 31 a 60 dias | L14: 34 | M14: P4
A15: =_xlfn.XLOOKUP(C:C,'Resumo por bucket'!F:F,'Resumo por bucket'!I:I,"") | B15: 87 | C15: PEDRA CALCARIA | D15: MATERIAL BASICO | E15: MARCOS ANTONIO DOS SANTOS BATISTA JUNIOR | F15: 73.175 | G15: 66.67 | H15: 4878.58 | I15: 250 | J15: 275 | K15: 31 a 60 dias | L15: 34 | M15: P4
A16: =_xlfn.XLOOKUP(C:C,'Resumo por bucket'!F:F,'Resumo por bucket'!I:I,"") | B16: 15847 | C16: SACOS RAFIA DE PP 50X63 LAM CONSTRUMAIS | D16: UTILIDADES E JARDIM | E16: CARUPLAST INDUSTRIA E COMERCIO LTDA | F16: 5334 | G16: 0.89 | H16: 4747.26 | I16: 2 | J16: 124.72 | K16: 31 a 60 dias | L16: 34 | M16: P4
A17: =_xlfn.XLOOKUP(C:C,'Resumo por bucket'!F:F,'Resumo por bucket'!I:I,"") | B17: 167 | C17: TELHA CANAL TIPO RUSSA 1a. | D17: COBERTURA | E17: CERAMICA CRISTO REY LTDA | F17: 4324 | G17: 0.96 | H17: 4151.04 | I17: 1.4 | J17: 45.83 | K17: 31 a 60 dias | L17: 34 | M17: P4
A18: =_xlfn.XLOOKUP(C:C,'Resumo por bucket'!F:F,'Resumo por bucket'!I:I,"") -> X | B18: 13801 | C18: TELA MOEDA FERRO 1.90CM ESP 580CM ALT 19.72 FURO PRENSAL | D18: MATERIAL BASICO | E18: PRENSAL INDUSTRIA METALURGICA LTDA | F18: 89.001 | G18: 44.33 | H18: 3945.41 | I18: 76 | J18: 71.45 | K18: Acima de 180 dias | L18: 276 | M18: P1
A19: =_xlfn.XLOOKUP(C:C,'Resumo por bucket'!F:F,'Resumo por bucket'!I:I,"") | B19: 147 | C19: COLUNA FERRO 5/16 8.00MM 07X17 | D19: MATERIAL BASICO | E19: ALUMIFER ALUMINIO E FERRO LTDA. | F19: 297.5 | G19: 12.34 | H19: 3671.15 | I19: 22 | J19: 78.35 | K19: 31 a 60 dias | L19: 34 | M19: P4
A20: =_xlfn.XLOOKUP(C:C,'Resumo por bucket'!F:F,'Resumo por bucket'!I:I,"") | B20: 11693 | C20: ABRACADEIRA NYLON BR 140X3.50 FOXLUX | D20: FERRAGEM | E20: ALMEIDA | F20: 59400.02 | G20: 0.06 | H20: 3564 | I20: 0.15 | J20: 150 | K20: 31 a 60 dias | L20: 34 | M20: P4
A21: =_xlfn.XLOOKUP(C:C,'Resumo por bucket'!F:F,'Resumo por bucket'!I:I,"") | B21: 148 | C21: COLUNA FERRO 3/8 10.00MM 07X17 | D21: MATERIAL BASICO | E21: ALUMIFER ALUMINIO E FERRO LTDA. | F21: 211 | G21: 16.79 | H21: 3542.69 | I21: 30 | J21: 78.73 | K21: 31 a 60 dias | L21: 34 | M21: P4
A22: =_xlfn.XLOOKUP(C:C,'Resumo por bucket'!F:F,'Resumo por bucket'!I:I,"") | B22: 15800 | C22: CERAMICA 46X46 BR.NEVE EXT 2.79M2 STELA | D22: CERAMICA | E22: PAMESA DO BRASIL S/A | F22: 225.99 | G22: 15.61 | H22: 3527.7 | I22: 32.9 | J22: 110.77 | K22: 31 a 60 dias | L22: 34 | M22: P4
A23: =_xlfn.XLOOKUP(C:C,'Resumo por bucket'!F:F,'Resumo por bucket'!I:I,"") | B23: 3822 | C23: PEDRA RACHINHA IRREGULAR | D23: MATERIAL BASICO | E23: SIDNEI PEREIRA RODRIGUES | F23: 162 | G23: 20 | H23: 3240 | I23: 30 | J23: 50 | K23: 31 a 60 dias | L23: 34 | M23: P4
A24: =_xlfn.XLOOKUP(C:C,'Resumo por bucket'!F:F,'Resumo por bucket'!I:I,"") -> 0 | B24: 14346 | C24: METALON GALV 30MM X 20MM 1.25MM - CH 18 | D24: MATERIAL BASICO | E24: ACO BRAZIL | F24: 47.2 | G24: 62.36 | H24: 2943.39 | I24: 95 | J24: 52.34 | K24: Nunca vendeu (14 meses)
A25: =_xlfn.XLOOKUP(C:C,'Resumo por bucket'!F:F,'Resumo por bucket'!I:I,"") -> 0 | B25: 8953 | C25: TORNEIRA MET FILTRO ABS BM 2172 C40 CR IMPERATRIZ METAIS | D25: MD-MD-MD-MD-MD- MD-MD-MD-MD-MD- | E25: MARTINS | F25: 27 | G25: 96.28 | H25: 2599.56 | I25: 160 | J25: 66.18 | K25: Nunca vendeu (14 meses)
A26: =_xlfn.XLOOKUP(C:C,'Resumo por bucket'!F:F,'Resumo por bucket'!I:I,"") | B26: 15996 | C26: TINTA EPOXI BA BICOMP P/SINALIZACAO CZ MEDIO BD 18L VIMASTER | D26: PINTURA | E26: VIMASTER INDUSTRIA E COMERCIO DE COMPONENTES DE VI | F26: 5 | G26: 513.84 | H26: 2569.2 | I26: 820 | J26: 59.58 | K26: 31 a 60 dias | L26: 34 | M26: P4
A27: =_xlfn.XLOOKUP(C:C,'Resumo por bucket'!F:F,'Resumo por bucket'!I:I,"") -> 0 | B27: 461 | C27: LINHA MISTA 3X6 BIT 5X13CM | D27: COBERTURA | E27: O ATACADAO DA MADEIRA | F27: 67.5011 | G27: 33.5 | H27: 2261.29 | I27: 52 | J27: 55.22 | K27: 121 a 150 dias | L27: 125 | M27: P3
A28: =_xlfn.XLOOKUP(C:C,'Resumo por bucket'!F:F,'Resumo por bucket'!I:I,"") -> 0 | B28: 15511 | C28: MADEIRITE PLASTIFICADO 1.10X2.20 18MM | D28: MATERIAL BASICO | E28: AMDS MADEIRAS E MATERIAIS DE CONSTRUCAO | F28: 10 | G28: 222 | H28: 2220 | I28: 340 | J28: 53.15 | K28: Acima de 180 dias | L28: 215 | M28: P2
A29: =_xlfn.XLOOKUP(C:C,'Resumo por bucket'!F:F,'Resumo por bucket'!I:I,"") | B29: 14355 | C29: CERAMICA MAR GRIGIO 45x45 CX 2M2 TIPO A RAVELLO | D29: CERAMICA | E29: CERAMICA CAPRI LTDA | F29: 94 | G29: 23.53 | H29: 2211.82 | I29: 35.9 | J29: 52.58 | K29: 31 a 60 dias | L29: 34 | M29: P4
A30: =_xlfn.XLOOKUP(C:C,'Resumo por bucket'!F:F,'Resumo por bucket'!I:I,"") -> 0 | B30: 16124 | C30: TELA ALAMBRADO PRACTICA FIO 2.400MM 5X15 ALT 1.57MT BELGO | D30: MATERIAL BASICO | F30: 50 | G30: 42.6 | H30: 2130 | I30: 80 | J30: 87.79 | K30: Nunca vendeu (14 meses)
A31: =_xlfn.XLOOKUP(C:C,'Resumo por bucket'!F:F,'Resumo por bucket'!I:I,"") | B31: 101 | C31: BLOCO P/LAJE 30X07X20 | D31: MATERIAL BASICO | E31: ANTONIO TEODOSIO NETO - ME | F31: 1384 | G31: 1.5 | H31: 2076 | I31: 2.5 | J31: 66.67 | K31: 31 a 60 dias | L31: 34 | M31: P4
A32: =_xlfn.XLOOKUP(C:C,'Resumo por bucket'!F:F,'Resumo por bucket'!I:I,"") | B32: 15801 | C32: CERAMICA 46X46 PIPA EXT 2.79M2 STELA | D32: CERAMICA | E32: PAMESA DO BRASIL S/A | F32: 119.97 | G32: 15.61 | H32: 1872.73 | I32: 32.9 | J32: 110.77 | K32: 31 a 60 dias | L32: 34 | M32: P4
A33: =_xlfn.XLOOKUP(C:C,'Resumo por bucket'!F:F,'Resumo por bucket'!I:I,"") | B33: 15802 | C33: CERAMICA 46X46 SUME BR EXT 2.79M2 STELA | D33: CERAMICA | E33: PAMESA DO BRASIL S/A | F33: 119.97 | G33: 15.61 | H33: 1872.73 | I33: 32.9 | J33: 110.77 | K33: 31 a 60 dias | L33: 34 | M33: P4
A34: =_xlfn.XLOOKUP(C:C,'Resumo por bucket'!F:F,'Resumo por bucket'!I:I,"") | B34: 115 | C34: CANALETA PREMOLDADA CINTA 09X10X33 | D34: MATERIAL BASICO | E34: RJ FERRAGENS | F34: 374 | G34: 5 | H34: 1870 | I34: 10 | J34: 100 | K34: 31 a 60 dias | L34: 34 | M34: P4
A35: =_xlfn.XLOOKUP(C:C,'Resumo por bucket'!F:F,'Resumo por bucket'!I:I,"") | B35: 14789 | C35: TELHA PVC INCOLOR ONDAFORT 2,44X1,1M FORTLEV | D35: COBERTURA | E35: FORTLEV BA | F35: 13 | G35: 140.68 | H35: 1828.84 | I35: 240 | J35: 70.6 | K35: 31 a 60 dias | L35: 34 | M35: P4
A36: =_xlfn.XLOOKUP(C:C,'Resumo por bucket'!F:F,'Resumo por bucket'!I:I,"") -> 0 | B36: 11161 | C36: BOB. TERMICA 80 X 40 MTS PERSONALIZADA | D36: MATERIAL DE USO E CONSUMO | E36: EUCLIDES JOAQUIM DE OLIVEIRA ME | F36: 630 | G36: 2.83 | H36: 1782.9 | I36: 2.85 | J36: 0.59 | K36: Nunca vendeu (14 meses)
A37: =_xlfn.XLOOKUP(C:C,'Resumo por bucket'!F:F,'Resumo por bucket'!I:I,"") | B37: 112 | C37: TINTA PO C/10KG CH-1 CAL MEGAO | D37: PINTURA | E37: EMPRESA NACIONAL DE MAT DE CONSTRU | F37: 72 | G37: 24.5 | H37: 1764 | I37: 36 | J37: 46.94 | K37: 31 a 60 dias | L37: 34 | M37: P4
A38: =_xlfn.XLOOKUP(C:C,'Resumo por bucket'!F:F,'Resumo por bucket'!I:I,"") -> 0 | B38: 2540 | C38: REBOCAL MULTIUSO CH1 SC C/20KG MIBRA | D38: IMPERMEABILIZANT ES | E38: MIBRA MINERIOS | F38: 71 | G38: 24.6 | H38: 1746.6 | I38: 40 | J38: 62.6 | K38: Acima de 180 dias | L38: 276 | M38: P1
A39: =_xlfn.XLOOKUP(C:C,'Resumo por bucket'!F:F,'Resumo por bucket'!I:I,"") | B39: 723 | C39: ARGAMASSA COLA FORTE AC-II 15KG POLIMASSA | D39: ARGAMASSAS E REJUNTE | E39: POLIMASSA ARGAMASSAS | F39: 100 | G39: 15.95 | H39: 1595 | I39: 24 | J39: 50.45 | K39: 31 a 60 dias | L39: 34 | M39: P4
A40: =_xlfn.XLOOKUP(C:C,'Resumo por bucket'!F:F,'Resumo por bucket'!I:I,"") -> 0 | B40: 15525 | C40: BACIA P/CAIXA ACOPL IZY CONFORTO BR DECA | D40: LOUCAS SANITARIA | E40: DEXCO S.A.. | F40: 3 | G40: 527.27 | H40: 1581.81 | I40: 770 | J40: 46.04 | K40: Nunca vendeu (14 meses)
A41: =_xlfn.XLOOKUP(C:C,'Resumo por bucket'!F:F,'Resumo por bucket'!I:I,"") | B41: 1718 | C41: TABUA MISTA 28CM BIT 2.2X28 | D41: MATERIAL BASICO | E41: AL MADEIRAS EIRELE ME | F41: 85.0004 | G41: 18.5 | H41: 1572.51 | I41: 32 | J41: 72.97 | K41: 31 a 60 dias | L41: 34 | M41: P4
A42: =_xlfn.XLOOKUP(C:C,'Resumo por bucket'!F:F,'Resumo por bucket'!I:I,"") -> 0 | B42: 11074 | C42: COLORANTE ICORES BA AZ INTENSO P0441 0.9L | D42: PINTURA | E42: TINTAS IQUINE LTDA. | F42: 6708.31 | G42: 0.23 | H42: 1542.91 | I42: 0.37 | J42: 60.01 | K42: Nunca vendeu (14 meses)
A43: =_xlfn.XLOOKUP(C:C,'Resumo por bucket'!F:F,'Resumo por bucket'!I:I,"") | B43: 458 | C43: LINHA MISTA 3X3 BIT 5X5CM | D43: COBERTURA | E43: O ATACADAO DA MADEIRA | F43: 158.5005 | G43: 9.3 | H43: 1474.05 | I43: 16 | J43: 72.04 | K43: 31 a 60 dias | L43: 34 | M43: P4
A44: =_xlfn.XLOOKUP(C:C,'Resumo por bucket'!F:F,'Resumo por bucket'!I:I,"") -> X | B44: 10442 | C44: PORCELANATO BALI POLIDO 61X61 CX 1.88M2 TIPO A CERCAMP | D44: CERAMICA | E44: Cerbras - Matriz | F44: 30.08 | G44: 48.84 | H44: 1469.11 | I44: 70 | J44: 43.33 | K44: Nunca vendeu (14 meses)
A45: =_xlfn.XLOOKUP(C:C,'Resumo por bucket'!F:F,'Resumo por bucket'!I:I,"") | B45: 2752 | C45: CABO FLEX 2.5MM BR PC MEGATRON | D45: MATERIAL ELETRICO | E45: MARTINS COM SERV DISTR SA | F45: 635 | G45: 2.21 | H45: 1403.35 | I45: 4 | J45: 80.95 | K45: 31 a 60 dias | L45: 34 | M45: P4
A46: =_xlfn.XLOOKUP(C:C,'Resumo por bucket'!F:F,'Resumo por bucket'!I:I,"") | B46: 2615 | C46: CABO FLEX 2.5MM AZ PC MEGATRON | D46: MATERIAL ELETRICO | E46: MARTINS COM SERV DISTR SA | F46: 626.8 | G46: 2.21 | H46: 1385.23 | I46: 4 | J46: 80.95 | K46: 31 a 60 dias | L46: 34 | M46: P4
A47: =_xlfn.XLOOKUP(C:C,'Resumo por bucket'!F:F,'Resumo por bucket'!I:I,"") -> X | B47: 11611 | C47: KIT ACO CACAU 40 COZIMAX | D47: ARMARIOS, GABINETES | E47: COZIMAX MOVEIS MIRASSOL LTDA | F47: 4 | G47: 342.51 | H47: 1370.04 | I47: 400 | J47: 16.78 | K47: Nunca vendeu (14 meses)
A48: =_xlfn.XLOOKUP(C:C,'Resumo por bucket'!F:F,'Resumo por bucket'!I:I,"") | B48: 10799 | C48: TRELICA TG8 SL 6/3, 4/4,2MM IND | D48: MATERIAL BASICO | E48: MEGA NORDESTE | F48: 321.95 | G48: 4.19 | H48: 1348.97 | I48: 9 | J48: 114.71 | K48: 31 a 60 dias | L48: 34 | M48: P4
A49: =_xlfn.XLOOKUP(C:C,'Resumo por bucket'!F:F,'Resumo por bucket'!I:I,"") | B49: 1863 | C49: TUBO PVC ESG 100MM SN KRONA | D49: HIDRAULICA | E49: PROJECTA MAT. DE CONST. LTDA | F49: 21.45 | G49: 61.9 | H49: 1327.75 | I49: 100 | J49: 61.55 | K49: 31 a 60 dias | L49: 34 | M49: P4
A50: =_xlfn.XLOOKUP(C:C,'Resumo por bucket'!F:F,'Resumo por bucket'!I:I,"") -> 0 | B50: 14437 | C50: BONE PERSONALIZADO CONSTRUMAIS | D50: MATERIAL DE USO E CONSUMO | F50: 50 | G50: 25 | H50: 1250 | I50: 42.5 | J50: 70 | K50: Nunca vendeu (14 meses)
A51: =_xlfn.XLOOKUP(C:C,'Resumo por bucket'!F:F,'Resumo por bucket'!I:I,"") | B51: 388 | C51: CAIXA DAGUA POLIETILENO 1000LTS FORTLEV | D51: RESERVATORIOS | E51: ATACADAO ECONOMICO COM DE MAT DE CONSTRUCAO LTDA | F51: 3 | G51: 414.99 | H51: 1244.97 | I51: 590 | J51: 42.17 | K51: 31 a 60 dias | L51: 34 | M51: P4
A52: =_xlfn.XLOOKUP(C:C,'Resumo por bucket'!F:F,'Resumo por bucket'!I:I,"") -> 0 | B52: 11859 | C52: PAPEL REPORT PR.A4 500F GR75 | D52: UTILIDADES E JARDIM | E52: MARTINS | F52: 46 | G52: 27.05 | H52: 1244.3 | I52: 34 | J52: 25.69 | K52: Nunca vendeu (14 meses)
A53: =_xlfn.XLOOKUP(C:C,'Resumo por bucket'!F:F,'Resumo por bucket'!I:I,"") | B53: 7457 | C53: MALHA POP PESADA Q-138 4.20MM 2X3 MALHA 10X10 | D53: MATERIAL BASICO | E53: ALUMIFER ALUMINIO E FERRO LTDA. | F53: 11 | G53: 111.84 | H53: 1230.24 | I53: 195 | J53: 74.35 | K53: 31 a 60 dias | L53: 34 | M53: P4
A54: =_xlfn.XLOOKUP(C:C,'Resumo por bucket'!F:F,'Resumo por bucket'!I:I,"") | B54: 10117 | C54: FITA MULT AUTO ADESIVA 60CM VEDATUDO DRYKO | D54: IMPERMEABILIZANT ES | E54: ALMEIDA | F54: 123 | G54: 9.86 | H54: 1212.78 | I54: 18 | J54: 82.63 | K54: 31 a 60 dias | L54: 34 | M54: P4
A55: =_xlfn.XLOOKUP(C:C,'Resumo por bucket'!F:F,'Resumo por bucket'!I:I,"") | B55: 9250 | C55: DIATEX PINTA MAIS BRANCO NEVE 15L | D55: PINTURA | E55: TINTAS IQUINE LTDA. | F55: 10 | G55: 115.42 | H55: 1154.2 | I55: 180 | J55: 55.96 | K55: 31 a 60 dias | L55: 34 | M55: P4
A56: =_xlfn.XLOOKUP(C:C,'Resumo por bucket'!F:F,'Resumo por bucket'!I:I,"") -> 0 | B56: 11603 | C56: SACOLA CAMISETA IMPRESSO/ALTA 70 x 90 x 0,03 | D56: MATERIAL DE USO E CONSUMO | E56: BIGFLEX EMBALAGENS LTDA | F56: 2000 | G56: 0.57 | H56: 1140 | I56: 0.3 | J56: 46.51 | K56: Nunca vendeu (14 meses)
A57: =_xlfn.XLOOKUP(C:C,'Resumo por bucket'!F:F,'Resumo por bucket'!I:I,"") | B57: 2206 | C57: TUBO PVC ESG 50MM SN KRONA | D57: HIDRAULICA | E57: PROJECTA MAT. DE CONST. LTDA | F57: 19.271 | G57: 58.99 | H57: 1136.8 | I57: 95 | J57: 61.04 | K57: 31 a 60 dias | L57: 34 | M57: P4
A58: =_xlfn.XLOOKUP(C:C,'Resumo por bucket'!F:F,'Resumo por bucket'!I:I,"") | B58: 3588 | C58: CABO FLEX 6.0MM AZ PC MEGATRON | D58: MATERIAL ELETRICO | E58: MARTINS COM SERV DISTR SA | F58: 200 | G58: 5.59 | H58: 1118 | I58: 10 | J58: 78.91 | K58: 31 a 60 dias | L58: 34 | M58: P4
A59: =_xlfn.XLOOKUP(C:C,'Resumo por bucket'!F:F,'Resumo por bucket'!I:I,"") | B59: 1320 | C59: CABO FLEX 2.5MM PT PC MEGATRON | D59: MATERIAL ELETRICO | E59: MARTINS COM SERV DISTR SA | F59: 484 | G59: 2.21 | H59: 1069.64 | I59: 4 | J59: 80.95 | K59: 31 a 60 dias | L59: 34 | M59: P4
A60: =_xlfn.XLOOKUP(C:C,'Resumo por bucket'!F:F,'Resumo por bucket'!I:I,"") | B60: 10797 | C60: BOTA COURO P/CONST BICO PVC 42 VULCAFLEX | D60: FERRAMENTAS | E60: MARLUVAS EQUIPAMENTOS DE SEGURANCA LTDA. | F60: 16 | G60: 66.44 | H60: 1063.04 | I60: 105 | J60: 58.04 | K60: 31 a 60 dias | L60: 34 | M60: P4
A61: =_xlfn.XLOOKUP(C:C,'Resumo por bucket'!F:F,'Resumo por bucket'!I:I,"") | B61: 1945 | C61: TUBO PVC SOLD 60MM SN KRONA | D61: HIDRAULICA | E61: PROJECTA MAT. DE CONST. LTDA | F61: 5.724 | G61: 182.45 | H61: 1044.34 | I61: 285 | J61: 56.21 | K61: 31 a 60 dias | L61: 34 | M61: P4
A62: =_xlfn.XLOOKUP(C:C,'Resumo por bucket'!F:F,'Resumo por bucket'!I:I,"") | B62: 8992 | C62: CIMENTO MONTES CLAROS CPII F 32 ACPY 50KG | D62: MATERIAL BASICO | E62: ELIZABETH CIMENTOS S/A | F62: 27.5 | G62: 37.9 | H62: 1042.25 | I62: 51 | J62: 34.56 | K62: 31 a 60 dias | L62: 34 | M62: P4
A63: =_xlfn.XLOOKUP(C:C,'Resumo por bucket'!F:F,'Resumo por bucket'!I:I,"") | B63: 11604 | C63: MOVEL DUPLO ABERTO | D63: MATERIAL DE USO E CONSUMO | E63: ASS BR P GESTAO DA LOG REVERSA PROD ILUM RECICLUS | F63: 1 | G63: 1030 | H63: 1030 | I63: 1030 | J63: 0 | K63: 31 a 60 dias | L63: 34 | M63: P4
A64: =_xlfn.XLOOKUP(C:C,'Resumo por bucket'!F:F,'Resumo por bucket'!I:I,"") | B64: 8666 | C64: CABO FLEX 6.0MM BR PC MEGATRON | D64: MATERIAL ELETRICO | E64: MARTINS COM SERV DISTR SA | F64: 184.01 | G64: 5.59 | H64: 1028.62 | I64: 10 | J64: 78.91 | K64: 31 a 60 dias | L64: 34 | M64: P4
A65: =_xlfn.XLOOKUP(C:C,'Resumo por bucket'!F:F,'Resumo por bucket'!I:I,"") -> 0 | B65: 12480 | C65: PORTA SEMI OCA MOGNO 2.10X0.60X30MM ALPHA | D65: ESQUADRIAS | E65: N L INDUSTRIA E COMERCIO DE PRODUTOS DE MADEIRA LT | F65: 10 | G65: 99.9 | H65: 999 | I65: 170 | J65: 70.17 | K65: Nunca vendeu (14 meses)
A66: =_xlfn.XLOOKUP(C:C,'Resumo por bucket'!F:F,'Resumo por bucket'!I:I,"") -> 0 | B66: 11269 | C66: ICORES DELANIL FOSCO BASE P 16L | D66: PINTURA | E66: TINTAS IQUINE LTDA. | F66: 4 | G66: 245.59 | H66: 982.36 | I66: 370 | J66: 50.66 | K66: Nunca vendeu (14 meses)
A67: =_xlfn.XLOOKUP(C:C,'Resumo por bucket'!F:F,'Resumo por bucket'!I:I,"") | B67: 2639 | C67: TUBO PVC SOLD 50MM SN KRONA | D67: HIDRAULICA | E67: PROJECTA MAT. DE CONST. LTDA | F67: 13.15 | G67: 74.5 | H67: 979.68 | I67: 115 | J67: 54.36 | K67: 31 a 60 dias | L67: 34 | M67: P4
A68: =_xlfn.XLOOKUP(C:C,'Resumo por bucket'!F:F,'Resumo por bucket'!I:I,"") -> 0 | B68: 14790 | C68: TELHA PVC INCOLOR ONDAFORT 3,05X1,1M FORTLEV | D68: COBERTURA | E68: FORTLEV BA | F68: 5 | G68: 194.17 | H68: 970.85 | I68: 335 | J68: 72.53 | K68: 121 a 150 dias | L68: 125 | M68: P3
A69: =_xlfn.XLOOKUP(C:C,'Resumo por bucket'!F:F,'Resumo por bucket'!I:I,"") | B69: 483 | C69: TELHA BRASILIT FIBROTEX 2.44X0.50X4MM | D69: COBERTURA | E69: ATACADAO ECONOMICO COM DE MAT DE CONSTRUCAO LTDA | F69: 37 | G69: 25.99 | H69: 961.63 | I69: 36 | J69: 38.51 | K69: 31 a 60 dias | L69: 34 | M69: P4
A70: =_xlfn.XLOOKUP(C:C,'Resumo por bucket'!F:F,'Resumo por bucket'!I:I,"") -> 0 | B70: 11602 | C70: SACOLA CAMISETA IMPRESSO/ALTA 50 x 70 x 0,03 | D70: MATERIAL DE USO E CONSUMO | E70: BIGFLEX EMBALAGENS LTDA | F70: 3000 | G70: 0.32 | H70: 960 | I70: 0.11 | J70: 64.34 | K70: Nunca vendeu (14 meses)
A71: =_xlfn.XLOOKUP(C:C,'Resumo por bucket'!F:F,'Resumo por bucket'!I:I,"") | B71: 16304 | C71: CABO FLEX PP 2X4.00MM MT MEGATROM | E71: MARTINS COM SERV DISTR SA | F71: 100 | G71: 9.35 | H71: 935 | I71: 17 | J71: 81.76 | K71: Sem historico (SKU novo)
A72: =_xlfn.XLOOKUP(C:C,'Resumo por bucket'!F:F,'Resumo por bucket'!I:I,"") | B72: 5485 | C72: CHAPA GALV 26 40CM ACO BRASIL | D72: MATERIAL BASICO | E72: COMPANHIA SIDERÚRGICA NACIONAL | F72: 47.4268 | G72: 19.39 | H72: 919.61 | I72: 25 | J72: 28.9 | K72: 31 a 60 dias | L72: 34 | M72: P4
A73: =_xlfn.XLOOKUP(C:C,'Resumo por bucket'!F:F,'Resumo por bucket'!I:I,"") | B73: 1865 | C73: TUBO PVC ESG 75MM SN KRONA | D73: HIDRAULICA | E73: PROJECTA MAT. DE CONST. LTDA | F73: 14.535 | G73: 62.9 | H73: 914.25 | I73: 105 | J73: 66.93 | K73: 31 a 60 dias | L73: 34 | M73: P4
A74: =_xlfn.XLOOKUP(C:C,'Resumo por bucket'!F:F,'Resumo por bucket'!I:I,"") -> 0 | B74: 14022 | C74: SACO RECICLADO IMPRESSO TRANSPARENTE 43X70 - KG | D74: MATERIAL DE USO E CONSUMO | E74: DOM PACK COMERCIO DE EMBALAGENS LTDA | F74: 50 | G74: 18 | H74: 900 | I74: 23.4 | J74: 30 | K74: Nunca vendeu (14 meses)
A75: =_xlfn.XLOOKUP(C:C,'Resumo por bucket'!F:F,'Resumo por bucket'!I:I,"") | B75: 15845 | C75: TELHA PVC PLAN 2.41X0.88M CERAMICA EPLAST | D75: COBERTURA | E75: MERCANTE & ROFE DISTRIBUIDORA LTDA | F75: 10 | G75: 89.51 | H75: 895.1 | I75: 135 | J75: 50.83 | K75: 31 a 60 dias | L75: 34 | M75: P4
A76: =_xlfn.XLOOKUP(C:C,'Resumo por bucket'!F:F,'Resumo por bucket'!I:I,"") -> 0 | B76: 9447 | C76: CABO FLEX PP 4X2.5MM MT MEGATRON | D76: MATERIAL ELETRICO | F76: 99.4155 | G76: 8.98 | H76: 892.75 | I76: 18 | J76: 100.44 | K76: 121 a 150 dias | L76: 125 | M76: P3
A77: =_xlfn.XLOOKUP(C:C,'Resumo por bucket'!F:F,'Resumo por bucket'!I:I,"") | B77: 456 | C77: CAIBRO SERRADO MISTO 3X5CM | D77: COBERTURA | E77: O ATACADAO DA MADEIRA | F77: 146.0003 | G77: 6.1 | H77: 890.6 | I77: 9.5 | J77: 55.74 | K77: 31 a 60 dias | L77: 34 | M77: P4
A78: =_xlfn.XLOOKUP(C:C,'Resumo por bucket'!F:F,'Resumo por bucket'!I:I,"") -> 0 | B78: 11090 | C78: ICORES LIMPA FACIL BASE C LT 16L | D78: PINTURA | E78: TINTAS IQUINE LTDA. | F78: 5 | G78: 177.1 | H78: 885.5 | I78: 300 | J78: 69.39 | K78: Nunca vendeu (14 meses)
A79: =_xlfn.XLOOKUP(C:C,'Resumo por bucket'!F:F,'Resumo por bucket'!I:I,"") | B79: 387 | C79: CAIXA DAGUA POLIETILENO 500LTS FORTLEV | D79: RESERVATORIOS | E79: MULTI SOLDAS COMERCIO LTDA. | F79: 4 | G79: 221.21 | H79: 884.84 | I79: 340 | J79: 53.7 | K79: 31 a 60 dias | L79: 34 | M79: P4
A80: =_xlfn.XLOOKUP(C:C,'Resumo por bucket'!F:F,'Resumo por bucket'!I:I,"") | B80: 1798 | C80: CABO FLEX PP 3X2.5MM 1.0KV MT MEGATRON | D80: MATERIAL ELETRICO | E80: MARTINS | F80: 118 | G80: 7.48 | H80: 882.64 | I80: 15 | J80: 100.66 | K80: 31 a 60 dias | L80: 34 | M80: P4
A81: =_xlfn.XLOOKUP(C:C,'Resumo por bucket'!F:F,'Resumo por bucket'!I:I,"") | B81: 14674 | C81: LONA PLASTICA 4M PT 36KG LONAX | D81: PINTURA | E81: BARTOFIL DISTRIBUIDORA SA | F81: 217 | G81: 4.03 | H81: 874.51 | I81: 9 | J81: 123.36 | K81: 31 a 60 dias | L81: 34 | M81: P4
A82: =_xlfn.XLOOKUP(C:C,'Resumo por bucket'!F:F,'Resumo por bucket'!I:I,"") | B82: 116 | C82: CANALETA PREMOLDADA RADIER 33X14X12 | D82: MATERIAL BASICO | E82: RJ FERRAGENS | F82: 144 | G82: 6 | H82: 864 | I82: 12 | J82: 100 | K82: 31 a 60 dias | L82: 34 | M82: P4
A83: =_xlfn.XLOOKUP(C:C,'Resumo por bucket'!F:F,'Resumo por bucket'!I:I,"") | B83: 1652 | C83: CALHA BEIRAL PVC 125MM C/3M BG TIGRE | D83: HIDRAULICA | E83: DISTRIBUIDORA ADAUTO CARVALHO LTDA | F83: 5 | G83: 172.29 | H83: 861.45 | I83: 260 | J83: 50.91 | K83: 31 a 60 dias | L83: 34 | M83: P4
A84: =_xlfn.XLOOKUP(C:C,'Resumo por bucket'!F:F,'Resumo por bucket'!I:I,"") -> 0 | B84: 9463 | C84: GONDOLA EXPOSITORA MOVEL CAIXA C/1 PECA | D84: MATERIAL DE USO E CONSUMO | E84: BLUKIT INDUSTRIA DE PLASTICOS LTDA | F84: 1 | G84: 856.64 | H84: 856.64 | I84: 0 | J84: -100 | K84: Nunca vendeu (14 meses)
A85: =_xlfn.XLOOKUP(C:C,'Resumo por bucket'!F:F,'Resumo por bucket'!I:I,"") -> 0 | B85: 9363 | C85: TEL CEL SAMS GLX A205G PTO-SP | D85: MATERIAL DE USO E CONSUMO | E85: MARTINS | F85: 1 | G85: 855.68 | H85: 855.68 | I85: 850 | J85: -0.66 | K85: Nunca vendeu (14 meses)
A86: =_xlfn.XLOOKUP(C:C,'Resumo por bucket'!F:F,'Resumo por bucket'!I:I,"") -> 0 | B86: 14149 | C86: REFLETOR LED 300W 18000LM 6500KBIV PT ECONOMAX | D86: ILUMINACAO | E86: NILO MAIA DISTRIBUIDORA LTDA | F86: 7 | G86: 121.86 | H86: 853.02 | I86: 200 | J86: 64.12 | K86: Nunca vendeu (14 meses)
A87: =_xlfn.XLOOKUP(C:C,'Resumo por bucket'!F:F,'Resumo por bucket'!I:I,"") | B87: 2492 | C87: CABO FLEX 2.5MM VERD PC MEGATRON | D87: MATERIAL ELETRICO | E87: MARTINS COM SERV DISTR SA | F87: 384.8 | G87: 2.21 | H87: 850.41 | I87: 4 | J87: 80.95 | K87: 31 a 60 dias | L87: 34 | M87: P4
A88: =_xlfn.XLOOKUP(C:C,'Resumo por bucket'!F:F,'Resumo por bucket'!I:I,"") | B88: 8607 | C88: REGISTRO PRESSAO MET 1/2 1416 C40 FXMSV DN15 6366 REAL METAIS | D88: METAIS | E88: REAL RECUPERADORA DE METAIS | F88: 21 | G88: 40.26 | H88: 845.46 | I88: 75 | J88: 86.27 | K88: 31 a 60 dias | L88: 34 | M88: P4
A89: =_xlfn.XLOOKUP(C:C,'Resumo por bucket'!F:F,'Resumo por bucket'!I:I,"") -> 0 | B89: 15526 | C89: CAIXA ACOPL C/DUO IZY CONFORTO BR DECA | D89: LOUCAS SANITARIA | E89: DEXCO S.A.. | F89: 3 | G89: 281.08 | H89: 843.24 | I89: 430 | J89: 52.98 | K89: Nunca vendeu (14 meses)
A90: =_xlfn.XLOOKUP(C:C,'Resumo por bucket'!F:F,'Resumo por bucket'!I:I,"") | B90: 13330 | C90: PORTA SEMI OCA MOGNO 2.10X0.70X30MM CLM | D90: ESQUADRIAS | E90: ALMEIDA | F90: 9 | G90: 92 | H90: 828 | I90: 170 | J90: 84.78 | K90: 31 a 60 dias | L90: 34 | M90: P4
A91: =_xlfn.XLOOKUP(C:C,'Resumo por bucket'!F:F,'Resumo por bucket'!I:I,"") | B91: 13112 | C91: GESSO COMPOSTO 1KG ITATIUNGA | D91: MATERIAL BASICO | E91: INDUSTRIA E COMERCIO DE ARGAMASSAS ITATIUNGA LTDA | F91: 534 | G91: 1.54 | H91: 822.36 | I91: 3 | J91: 95.1 | K91: 31 a 60 dias | L91: 34 | M91: P4
A92: =_xlfn.XLOOKUP(C:C,'Resumo por bucket'!F:F,'Resumo por bucket'!I:I,"") -> 0 | B92: 11079 | C92: COLORANTE ICORES BA ROSA P0471 0.9L | D92: PINTURA | E92: TINTAS IQUINE LTDA. | F92: 6323.96 | G92: 0.13 | H92: 822.11 | I92: 0.21 | J92: 65 | K92: Nunca vendeu (14 meses)
A93: =_xlfn.XLOOKUP(C:C,'Resumo por bucket'!F:F,'Resumo por bucket'!I:I,"") | B93: 3210 | C93: TELHA BRASILIT FIBROTEX 2.44X1.10X5MM | D93: COBERTURA | E93: ATACADAO ECONOMICO COM DE MAT DE CONSTRUCAO LTDA | F93: 10 | G93: 81.9 | H93: 819 | I93: 120 | J93: 46.52 | K93: 31 a 60 dias | L93: 34 | M93: P4
A94: =_xlfn.XLOOKUP(C:C,'Resumo por bucket'!F:F,'Resumo por bucket'!I:I,"") | B94: 3718 | C94: CABO FLEX 4.0MM VERD PC MEGATRON | D94: MATERIAL ELETRICO | E94: MARTINS COM SERV DISTR SA | F94: 217.1 | G94: 3.72 | H94: 807.61 | I94: 7 | J94: 88.36 | K94: 31 a 60 dias | L94: 34 | M94: P4
A95: =_xlfn.XLOOKUP(C:C,'Resumo por bucket'!F:F,'Resumo por bucket'!I:I,"") -> 0 | B95: 13969 | C95: CORTADOR PIS/AZUL 120CM FAMASTIL | D95: FERRAMENTAS | E95: MARTINS | F95: 2 | G95: 402.78 | H95: 805.56 | I95: 700 | J95: 73.79 | K95: Nunca vendeu (14 meses)
A96: =_xlfn.XLOOKUP(C:C,'Resumo por bucket'!F:F,'Resumo por bucket'!I:I,"") | B96: 11014 | C96: BOTA COURO P/CONST BICO PVC 43 VULCAFLEX | D96: FERRAMENTAS | E96: MARLUVAS EQUIPAMENTOS DE SEGURANCA LTDA. | F96: 12 | G96: 66.63 | H96: 799.56 | I96: 100 | J96: 50.07 | K96: 31 a 60 dias | L96: 34 | M96: P4
A97: =_xlfn.XLOOKUP(C:C,'Resumo por bucket'!F:F,'Resumo por bucket'!I:I,"") -> 0 | B97: 11199 | C97: BOTA COURO P/CONST BICO ACO 41 VULCAFLEX | D97: FERRAMENTAS | E97: MARLUVAS EQUIPAMENTOS DE SEGURANCA LTDA. | F97: 12 | G97: 66.44 | H97: 797.28 | I97: 105 | J97: 58.04 | K97: 121 a 150 dias | L97: 125 | M97: P3
A98: =_xlfn.XLOOKUP(C:C,'Resumo por bucket'!F:F,'Resumo por bucket'!I:I,"") -> 0 | B98: 10016 | C98: CABO FLEX PP 3X4.0MM MT CORFIO | D98: MATERIAL ELETRICO | E98: MARTINS | F98: 65 | G98: 12.26 | H98: 796.9 | I98: 24 | J98: 95.76 | K98: Nunca vendeu (14 meses)
A99: =_xlfn.XLOOKUP(C:C,'Resumo por bucket'!F:F,'Resumo por bucket'!I:I,"") | B99: 2294 | C99: CABO FLEX 6.0MM PT PC MEGATRON | D99: MATERIAL ELETRICO | E99: MARTINS COM SERV DISTR SA | F99: 145 | G99: 5.49 | H99: 796.05 | I99: 10 | J99: 82.01 | K99: 31 a 60 dias | L99: 34 | M99: P4
A100: =_xlfn.XLOOKUP(C:C,'Resumo por bucket'!F:F,'Resumo por bucket'!I:I,"") | B100: 170 | C100: ARGAMASSA COLA FORTE AC-I 15KG POLIMASSA | D100: ARGAMASSAS E REJUNTE | E100: POLIMASSA ARGAMASSAS | F100: 99 | G100: 8 | H100: 792 | I100: 13 | J100: 62.54 | K100: 31 a 60 dias | L100: 34 | M100: P4
...

Sheet Resumo por bucket
A1: Bucket de giro (dias sem venda, aproximado) | B1: SKUs | C1: Valor em estoque (R$) | D1: % do total | F1: Rótulos de Linha | G1: Qtde! | H1: Valor! | I1: Filtro
A2: Ate 30 dias | B2: 0 | C2: 0 | D2: 0 | F2: 31 a 60 dias | G2: 95395.743 | H2: 285984.75
A3: 31 a 60 dias | B3: 1888 | C3: 426567.77 | D3: 48.23 | F3: 121 a 150 dias | G3: 358.9166 | H3: 6059.72
A4: 61 a 90 dias | B4: 0 | C4: 0 | D4: 0 | F4: LINHA MISTA 3X6 BIT 5X13CM | G4: 67.5011 | H4: 2261.29
A5: 91 a 120 dias | B5: 0 | C5: 0 | D5: 0 | F5: TELHA PVC INCOLOR ONDAFORT 3,05X1,1M FORTLEV | G5: 5 | H5: 970.85
A6: 121 a 150 dias | B6: 536 | C6: 45164.61 | D6: 5.11 | F6: CABO FLEX PP 4X2.5MM MT MEGATRON | G6: 99.4155 | H6: 892.75
A7: 151 a 180 dias | B7: 0 | C7: 0 | D7: 0 | F7: BOTA COURO P/CONST BICO ACO 41 VULCAFLEX | G7: 12 | H7: 797.28
A8: Acima de 180 dias | B8: 619 | C8: 53846.38 | D8: 6.09 | F8: CABO FLEX 4.0MM AZ PC MEGATRON | G8: 170 | H8: 576.3
A9: Nunca vendeu (14 meses) | B9: 1733 | C9: 351523.17 | D9: 39.75 | F9: DIALINE ESM SINT BR NEVE 3.0L | G9: 5 | H9: 561.25
A10: Sem historico (SKU novo) | B10: 68 | C10: 7254.58 | D10: 0.82 | F10: Acima de 180 dias | G10: 440.401 | H10: 12743.03
A11: TOTAL | B11: 4844 | C11: 884356.51 | D11: 100 | F11: TELA MOEDA FERRO 1.90CM ESP 580CM ALT 19.72 FURO PRENSAL | G11: 89.001 | H11: 3945.41 | I11: X
F12: MADEIRITE PLASTIFICADO 1.10X2.20 18MM | G12: 10 | H12: 2220
F13: REBOCAL MULTIUSO CH1 SC C/20KG MIBRA | G13: 71 | H13: 1746.6
F14: TELHA TRANSLUCIDA LEITOSA 2.44X1.10 GRANPLAST | G14: 7 | H14: 764.05
F15: ESCADA ALUM 05 DEG MOR | G15: 5 | H15: 742.8
F16: REFLETOR LED 200W PT 6500K BIV AVANT | G16: 8 | H16: 734.96
F17: PORTA SANF PVC 2.10X0.70CM BR NOVA FORMA | G17: 9 | H17: 729.99
F18: FORRO PVC LISO 200X7X4MT NOVA FORMA | G18: 34.4 | H18: 670.11 | I18: X
F19: CALHA BEIRAL PVC C/3M CAL/CKBR ASTRA | G19: 7 | H19: 649.11
F20: CHUMBADOR PBA 1/2 X 4.1/4 12414C ANCORA | G20: 200 | H20: 540
F21: Nunca vendeu (14 meses) | G21: 58475.62 | H21: 219342.29
F22: CUMEEIRA ZINCALUM 0.43 | G22: 2998 | H22: 77948
F23: VARETA SOLDA OXI 1.59MM GERDAU | G23: 7329 | H23: 74755.8
F24: SACOLA RECICLADAS VD 60X80 | G24: 1015 | H24: 11672.5
F25: TUBO PVC ROSCA 1 POL TIGRE | G25: 999.83 | H25: 8058.63
F26: METALON GALV 30MM X 20MM 1.25MM - CH 18 | G26: 47.2 | H26: 2943.39
F27: TORNEIRA MET FILTRO ABS BM 2172 C40 CR IMPERATRIZ METAIS | G27: 27 | H27: 2599.56
F28: TELA ALAMBRADO PRACTICA FIO 2.400MM 5X15 ALT 1.57MT BELGO | G28: 50 | H28: 2130
F29: BOB. TERMICA 80 X 40 MTS PERSONALIZADA | G29: 630 | H29: 1782.9
F30: BACIA P/CAIXA ACOPL IZY CONFORTO BR DECA | G30: 3 | H30: 1581.81
F31: COLORANTE ICORES BA AZ INTENSO P0441 0.9L | G31: 6708.31 | H31: 1542.91
F32: PORCELANATO BALI POLIDO 61X61 CX 1.88M2 TIPO A CERCAMP | G32: 30.08 | H32: 1469.11 | I32: X
F33: KIT ACO CACAU 40 COZIMAX | G33: 4 | H33: 1370.04 | I33: X
F34: BONE PERSONALIZADO CONSTRUMAIS | G34: 50 | H34: 1250
F35: PAPEL REPORT PR.A4 500F GR75 | G35: 46 | H35: 1244.3
F36: SACOLA CAMISETA IMPRESSO/ALTA 70 x 90 x 0,03 | G36: 2000 | H36: 1140
F37: PORTA SEMI OCA MOGNO 2.10X0.60X30MM ALPHA | G37: 10 | H37: 999
F38: ICORES DELANIL FOSCO BASE P 16L | G38: 4 | H38: 982.36
F39: SACOLA CAMISETA IMPRESSO/ALTA 50 x 70 x 0,03 | G39: 3000 | H39: 960
F40: SACO RECICLADO IMPRESSO TRANSPARENTE 43X70 - KG | G40: 50 | H40: 900
F41: ICORES LIMPA FACIL BASE C LT 16L | G41: 5 | H41: 885.5
F42: GONDOLA EXPOSITORA MOVEL CAIXA C/1 PECA | G42: 1 | H42: 856.64
F43: TEL CEL SAMS GLX A205G PTO-SP | G43: 1 | H43: 855.68
F44: REFLETOR LED 300W 18000LM 6500KBIV PT ECONOMAX | G44: 7 | H44: 853.02
F45: CAIXA ACOPL C/DUO IZY CONFORTO BR DECA | G45: 3 | H45: 843.24
... F50: TELEFONE CELULAR SAMSUNG GLX A013M PTO SP | G50: 1 | H50: 758.81
F51: ICORES DECORATTO MARM BASE P/M 20KG | G51: 3 | H51: 757.8 | I51: X
F52: SACOLAS 40X50 IMP. | G52: 5000 | H52: 750
F53: ICORES LIMPA FACIL BASE P LT 16L | G53: 2 | H53: 710.66
F54: LINHA MASSARANDUBA 3X6 5,50 X 13 | G54: 16 | H54: 691.2
F55: COLORANTE ICORES BA AMARELO P0411 0.9L | G55: 4539.26 | H55: 680.89
F56: ESCADA ALUM 08 DEG BOTAFOGO | G56: 3 | H56: 669.21
F57: TELHA PVC INCOLOR ONDAFORT 1,83X1,1M FORTLEV | G57: 6 | H57: 664.74
F58: ICORES DELANIL FOSCO BASE M L 16L | G58: 3 | H58: 659.25
F59: COLORANTE ICORES BA LARANJA P0501 0.9L | G59: 6111.2 | H59: 611.12
F60: BOBINA PRAT 79MM M80 40M 30X1 48G | G60: 150 | H60: 588
F61: TELHA BRASILIT FIBROTEX 2.13X1.10X6MM | G61: 8 | H61: 571.84
F62: TELHA PVC INCOLOR ONDAFORT 1,53X1,1M FORTLEV | G62: 6 | H62: 555.78
F63: LUVA SOLD BUCHA LATAO 32X1 AMANCO | G63: 34 | H63: 550.8
... F71: TRANSFORMADOR 2000VA BLIND TRIPOLAR INDUSAT | G71: 4 | H71: 522.32
F72: SPOT LED DIRECT MR16 BASE LINEAR 3X4W 6500K TASCHIBRA | G72: 4 | H72: 507.36 | I72: X
F73: ICORES DECORATTO MARM BASE P/M 4 KG | G73: 9 | H73: 504.63 | I73: X
F74: DIAPISO SUPER RESIST AMAR DEMARCACAO 18L | G74: 2 | H74: 503.56
F75: COLORANTE ICORES BA VERM OXIDO P0511 0.9L | G75: 5592.78 | H75: 503.35
F76: CARRO DE MAO 45L METAL PT NOVE54 | G76: 5 | H76: 502.1
F77: COLORANTE ICORES BA BRANCO P0451 0.9L | G77: 2949 | H77: 501.33
F78: Sem historico (SKU novo) | G78: 196 | H78: 1470.68
F79: Total Geral | G79: 154866.68 | H79: 525600.47

Sheet Ativo imobilizado (excluido)
A1: Itens de ativo imobilizado da propria loja (nao sao mercadoria de revenda), excluidos do ranking comercial acima, mesmo criterio ja usado nos periodos de Curva ABC (13 itens de ativo imobilizado excluidos da analise comercial).
A2: codigo | B2: produto | C2: categoria | D2: qtde | E2: valor_custo | F2: bucket_giro
A3: 9928 | B3: NOTE LENOVO IDEAPAD S145 I5 8GB 1TB WIN 10 PRATA | C3: ATIVO IMOBILIZADO | D3: 1 | E3: 2499 | F3: 31 a 60 dias
A4: 14160 | B4: TRICICLO MARCA TUKA MOD TK1200W COR AZ ANO/MOD 24/24 | C4: ATIVO IMOBILIZADO | D4: 1 | E4: 26000.4 | F4: 31 a 60 dias

Sheet Outliers criticos (excluidos)
A1: Itens com quantidade/custo em forte desacordo com os pares da mesma linha, pendente de confirmacao do Tony. Excluidos do ranking e dos totais acima. Ver diagnostico-giro-estoque.md, secao 03-08-2026, para o detalhe completo do benchmark.
A2: codigo | B2: produto | C2: categoria
A3: 7153 | B3: CABO FLEX 2.5MM AZ PC COBRECOM | C3: MATERIAL ELETRICO
A4: 7874 | B4: MANGUEIRA CORRUGADA 20MM AM - KRONA | C4: HIDRAULICA
